setup.py
Sorrex.egg-info/PKG-INFO
Sorrex.egg-info/SOURCES.txt
Sorrex.egg-info/dependency_links.txt
Sorrex.egg-info/top_level.txt
sorrex/__init__.py
sorrex/colors.py
sorrex/parser.code
sorrex/parser.py
sorrex/parser.pyy