Metadata-Version: 1.0
Name: Sorrex
Version: 1.2.0
Summary: Sorrex parser in Python.
Home-page: http://code.google.com/p/sorrex/
Author: ruby-U
Author-email: ruby.u.g@gmail.com
License: MIT
Platform: Any
Classifier: Development Status :: 4 - Beta
Classifier: Environment :: Console
Classifier: License :: OSI Approved :: MIT License
Classifier: Operating System :: OS Independent
Classifier: Topic :: Software Development :: Libraries :: Python Modules
Classifier: Natural Language :: Japanese
Classifier: Topic :: Text Processing
